process_fastq/__init__.py
process_fastq/cli.py
process_fastq/get_directory_paths.py
process_fastq/get_fastq_information.py
process_fastq/helper.py
process_fastq/process_fastq.py
process_fastq/run_cutadapt.py
process_fastq-2.1.3.dist-info/AUTHORS.rst
process_fastq-2.1.3.dist-info/LICENSE
process_fastq-2.1.3.dist-info/METADATA
process_fastq-2.1.3.dist-info/WHEEL
process_fastq-2.1.3.dist-info/entry_points.txt
process_fastq-2.1.3.dist-info/top_level.txt
process_fastq-2.1.3.dist-info/RECORD
